crewcharge_core/__init__.py
crewcharge_core/crewcharge.py
crewcharge_core-1.0.1.dist-info/METADATA
crewcharge_core-1.0.1.dist-info/WHEEL
crewcharge_core-1.0.1.dist-info/top_level.txt
crewcharge_core-1.0.1.dist-info/RECORD
